iv2py.cpython-38-x86_64-linux-gnu.so
iv2py-0.6.1.dist-info/top_level.txt
iv2py-0.6.1.dist-info/RECORD
iv2py-0.6.1.dist-info/METADATA
iv2py-0.6.1.dist-info/WHEEL
iv2py.libs/libgomp-24e2ab19.so.1.0.0
