Metadata-Version: 2.2
Name: iv2py
Version: 0.6.1
Summary: IV2py bioinformatic utilities
Author-email: Simon Gene Gottlieb <iv2py.simon@gottliebtfreitag.de>
Project-URL: Homepage, https://github.com/iv-project/IV2py
Classifier: Development Status :: 4 - Beta
Classifier: Natural Language :: English
Classifier: Topic :: Scientific/Engineering :: Bio-Informatics
Requires-Python: >=3.7
